skself/__init__.py
skself/test.py
skself/utils.py
skself/partial_annotations/__init__.py
skself/partial_annotations/lazy_model.py
skself-0.1.0.dist-info/LICENSE
skself-0.1.0.dist-info/METADATA
skself-0.1.0.dist-info/WHEEL
skself-0.1.0.dist-info/top_level.txt
skself-0.1.0.dist-info/RECORD
