Metadata-Version: 2.1
Name: skself
Version: 0.1.0
Summary: Self-supervised learning sklearn-style
Home-page: https://github.com/thetoby9944/skself
Author: thetoby9944
Author-email: thetoby@web.de
Classifier: Development Status :: 4 - Beta
Classifier: Intended Audience :: Science/Research
Classifier: Intended Audience :: Developers
Classifier: Programming Language :: Python :: 3
Classifier: Programming Language :: Python :: 3.7
Classifier: Programming Language :: Python :: 3.8
Classifier: Programming Language :: Python :: 3.9
Classifier: License :: OSI Approved :: GNU Affero General Public License v3 or later (AGPLv3+)
License-File: LICENSE
Requires-Dist: tqdm ~=4.19
Requires-Dist: pydantic ~=1.9
Requires-Dist: scikit-learn
Requires-Dist: segmentation-models
Requires-Dist: tfaugmentor
Requires-Dist: opencv-python-headless
Requires-Dist: Pillow
Requires-Dist: rich[jupyter]
Requires-Dist: pandas-profiling
Requires-Dist: matplotlib
Requires-Dist: scikit-image
